{
  "users": [
    {
      "email": "kitae@kitae.kitae",
      "password": "$2a$10$GQgtYHFn8r3DTSIcVEEQB.aoDR1x/lv8wVkgraGpaeD4NFUlx.0Wq",
      "username": "kitae",
      "id": 1
    },
    {
      "email": "test@test.com",
      "password": "$2a$10$.KCxI94dHxB3m7Sux.b8Oux9i9afxfZtCWLoC0hYL9rVPUVAAtrFC",
      "username": "aa",
      "id": 2
    },
    {
      "email": "test2@test.com",
      "password": "$2a$10$YalhQy8j9G3NjC7T3Aplb.kesMx4vOmvIkEf69SsVIcI5wiopdo4m",
      "username": "test2",
      "id": 3
    },
    {
      "email": "choiys1103@naver.com",
      "password": "$2a$10$uI8L1CTgElRHF578EjX9p.laW4ajGKcc.cE14JRh8KTqhzi4K14Wi",
      "username": "ys",
      "id": 4
    },
    {
      "email": "test8@test.com",
      "password": "$2a$10$V7p1ibIOKh6R/BZ2AWTFB.lZMPPWFYHJgC2iwgRR9QcmJ9R2r5eD2",
      "username": "test8",
      "id": 5
    },
    {
      "email": "sss@sss.com",
      "password": "$2a$10$CMXOf1uNh.0yRJULMS7L9OJkhOl0jYmbDgwbVUoA6sREi5lq.qLwW",
      "username": "ㅇㅇㅇㅇ",
      "id": 6
    }
  ],
  "login": [],
  "likes": [
    {
      "id": 1,
      "likes": 77
    }
  ],
  "bookmark": [
    {
      "email": "kitae@kitae.kitae",
      "postid": 1
    }
  ],
  "posts": [
    {
      "email": "test2@test.com",
      "username": "test2",
      "status": "help",
      "timeStamp": 1691842762952,
      "title": "집 지어주세요",
      "content": "집이 무너졌어요",
      "category": "조립",
      "date": "2023년 8월 27일",
      "time": "21:19",
      "price": "134,254,364",
      "position": {
        "lat": 37.5655362526725,
        "lng": 126.98145970410191,
        "addr": "서울 중구 을지로가 "
      },
      "img": "https://firebasestorage.googleapis.com/v0/b/please-b08ba.appspot.com/o/Image%2Fabc66ba8-9c80-fbf9-d6b3-0d7dc7a30eca?alt=media&token=a297b5ac-6cff-41bd-8930-0de368ac1f1e",
      "id": 1
    },
    {
      "email": "test@test.com",
      "username": "test",
      "status": "help",
      "timeStamp": 1691850271726,
      "title": "1234",
      "content": "13412",
      "category": "역할 대행",
      "date": "2023년 8월 22일",
      "time": "23:24",
      "price": "123,412",
      "position": {
        "lat": 37.5655362526725,
        "lng": 126.98145970410191,
        "addr": "서울 중구 을지로가 "
      },
      "img": "https://firebasestorage.googleapis.com/v0/b/please-b08ba.appspot.com/o/Image%2Ff5c857e8-ff4f-2f42-e6ae-ed9f628b3375?alt=media&token=abf19305-9144-4cd3-b1d1-cda4f9d007c0",
      "id": 2
    }
  ],
  "msg": [
    {
      "postId": 2,
      "toUser": "test@test.com",
      "fromUser": "test2@test.com",
      "fromUsername": "test2",
      "timeStamp": 1691852167268,
      "content": "ㅋㅋㅋㅋ",
      "id": 1
    }
  ]
}
